{
  "name": "Stripe",
  "notes": "",
  "dpi": 300,
  "live": true,
  "psize": "letter",
  "pori": "landscape",
  "csize": "small",
  "cori": "portrait",
  "cheight": "",
  "cwidth": "",
  "cunit": "mm",
  "ccircle": false,
  "gsize": 1,
  "gunit": "mm",
  "msize": 0.5,
  "munit": "in",
  "blsize": 0,
  "blunit": "in",
  "ssize": 0,
  "sunit": "in",
  "cutline": false,
  "bradius": 0,
  "brunit": "in",
  "overlay": false,
  "oopa": 0.5,
  "oURL": "",
  "extCSS": "",
  "css": "div {\n\tmargin:0;\n  \tborder:0;\n}\n\ndiv:nth-child(4n) {\n \tborder-top:5pt solid purple;\n}\ndiv:nth-child(4n+1) {\n \tborder-top:2pt solid whitesmoke;\n}\ndiv:nth-child(4n+2) {\n \tborder-top:4pt solid steelblue;\n}\ndiv:nth-child(4n+3) {\n \tborder-top:12pt solid #156;\n}",
  "csv": "",
  "mustache": "<div></div>\n<div></div>\n<div></div>\n<div></div>\n\n<div></div>\n<div></div>\n<div></div>\n<div></div>\n\n<div></div>\n<div></div>\n<div></div>\n<div></div>\n\n<div></div>\n<div></div>\n<div></div>\n<div></div>\n<div></div>\n<div></div>\n<div></div>\n<div></div>\n\n<div></div>\n<div></div>\n<div></div>\n<div></div>\n<div></div>\n<div></div>\n<div></div>\n<div></div>\n\n<div></div>\n<div></div>\n<div></div>\n<div></div>\n<div></div>\n<div></div>\n<div></div>\n<div></div>\n\n<div></div>\n<div></div>\n<div></div>\n<div></div>\n<div></div>\n<div></div>\n<div></div>\n<div></div>\n\n<div></div>\n<div></div>\n<div></div>\n<div></div>",
  "useMustache": false,
  "cardClass": "",
  "rscount": 1,
  "rsstyle": "bunch"
}